simplify_polygon.cpython-37m-x86_64-linux-gnu.so
find_contours.cpython-37m-x86_64-linux-gnu.so
draw_polygon.cpython-37m-x86_64-linux-gnu.so
run_length_encoding.cpython-37m-x86_64-linux-gnu.so
upolygon-0.1.11.dist-info/top_level.txt
upolygon-0.1.11.dist-info/LICENSE
upolygon-0.1.11.dist-info/RECORD
upolygon-0.1.11.dist-info/WHEEL
upolygon-0.1.11.dist-info/METADATA
upolygon/__init__.py
