Metadata-Version: 2.1
Name: upolygon
Version: 0.1.11
Summary: Collection of fast polygon operations for DL
Home-page: https://github.com/v7labs/upolygon
Author: V7
Author-email: simon@v7labs.com
Classifier: Programming Language :: Python :: 3
Classifier: License :: OSI Approved :: MIT License
Requires-Python: >=3.6
License-File: LICENSE
Requires-Dist: numpy
